synmax_agent/hyperion.py
synmax_agent-0.1.2.dist-info/METADATA
synmax_agent-0.1.2.dist-info/WHEEL
synmax_agent-0.1.2.dist-info/top_level.txt
synmax_agent-0.1.2.dist-info/RECORD
